[{"cost":{"resources":{"wood":580,"clay":460,"iron":350,"crop":180},"freeCrop":1},"buildingTime":2000},{"cost":{"resources":{"wood":740,"clay":590,"iron":450,"crop":230},"freeCrop":1},"buildingTime":2620},{"cost":{"resources":{"wood":950,"clay":755,"iron":575,"crop":295},"freeCrop":1},"buildingTime":3340},{"cost":{"resources":{"wood":1215,"clay":965,"iron":735,"crop":375},"freeCrop":1},"buildingTime":4170},{"cost":{"resources":{"wood":1555,"clay":1235,"iron":940,"crop":485},"freeCrop":1},"buildingTime":5140},{"cost":{"resources":{"wood":1995,"clay":1580,"iron":1205,"crop":620},"freeCrop":1},"buildingTime":6260},{"cost":{"resources":{"wood":2550,"clay":2025,"iron":1540,"crop":790},"freeCrop":1},"buildingTime":7570},{"cost":{"resources":{"wood":3265,"clay":2590,"iron":1970,"crop":1015},"freeCrop":1},"buildingTime":9080},{"cost":{"resources":{"wood":4180,"clay":3315,"iron":2520,"crop":1295},"freeCrop":1},"buildingTime":10830},{"cost":{"resources":{"wood":5350,"clay":4245,"iron":3230,"crop":1660},"freeCrop":1},"buildingTime":12860},{"cost":{"resources":{"wood":6845,"clay":5430,"iron":4130,"crop":2125},"freeCrop":2},"buildingTime":15220},{"cost":{"resources":{"wood":8765,"clay":6950,"iron":5290,"crop":2720},"freeCrop":2},"buildingTime":17950},{"cost":{"resources":{"wood":11220,"clay":8900,"iron":6770,"crop":3480},"freeCrop":2},"buildingTime":21130},{"cost":{"resources":{"wood":14360,"clay":11390,"iron":8665,"crop":4455},"freeCrop":2},"buildingTime":24810},{"cost":{"resources":{"wood":18380,"clay":14580,"iron":11090,"crop":5705},"freeCrop":2},"buildingTime":29080},{"cost":{"resources":{"wood":23530,"clay":18660,"iron":14200,"crop":7300},"freeCrop":2},"buildingTime":34030},{"cost":{"resources":{"wood":30115,"clay":23885,"iron":18175,"crop":9345},"freeCrop":2},"buildingTime":39770},{"cost":{"resources":{"wood":38550,"clay":30570,"iron":23260,"crop":11965},"freeCrop":2},"buildingTime":46440},{"cost":{"resources":{"wood":49340,"clay":39130,"iron":29775,"crop":15315},"freeCrop":2},"buildingTime":54170},{"cost":{"resources":{"wood":63155,"clay":50090,"iron":38110,"crop":19600},"freeCrop":2},"buildingTime":63130}]