[{"cost":{"resources":{"wood":110,"clay":160,"iron":70,"crop":60},"freeCrop":0},"buildingTime":2000},{"cost":{"resources":{"wood":140,"clay":205,"iron":90,"crop":75},"freeCrop":0},"buildingTime":2620},{"cost":{"resources":{"wood":180,"clay":260,"iron":115,"crop":100},"freeCrop":0},"buildingTime":3340},{"cost":{"resources":{"wood":230,"clay":335,"iron":145,"crop":125},"freeCrop":0},"buildingTime":4170},{"cost":{"resources":{"wood":295,"clay":430,"iron":190,"crop":160},"freeCrop":0},"buildingTime":5140},{"cost":{"resources":{"wood":380,"clay":550,"iron":240,"crop":205},"freeCrop":1},"buildingTime":6260},{"cost":{"resources":{"wood":485,"clay":705,"iron":310,"crop":265},"freeCrop":1},"buildingTime":7570},{"cost":{"resources":{"wood":620,"clay":900,"iron":395,"crop":340},"freeCrop":1},"buildingTime":9080},{"cost":{"resources":{"wood":795,"clay":1155,"iron":505,"crop":430},"freeCrop":1},"buildingTime":10830},{"cost":{"resources":{"wood":1015,"clay":1475,"iron":645,"crop":555},"freeCrop":1},"buildingTime":12860},{"cost":{"resources":{"wood":1300,"clay":1890,"iron":825,"crop":710},"freeCrop":1},"buildingTime":15220},{"cost":{"resources":{"wood":1660,"clay":2420,"iron":1060,"crop":905},"freeCrop":1},"buildingTime":17950},{"cost":{"resources":{"wood":2130,"clay":3095,"iron":1355,"crop":1160},"freeCrop":1},"buildingTime":21130},{"cost":{"resources":{"wood":2725,"clay":3960,"iron":1735,"crop":1485},"freeCrop":1},"buildingTime":24810},{"cost":{"resources":{"wood":3485,"clay":5070,"iron":2220,"crop":1900},"freeCrop":1},"buildingTime":29080},{"cost":{"resources":{"wood":4460,"clay":6490,"iron":2840,"crop":2435},"freeCrop":2},"buildingTime":34030},{"cost":{"resources":{"wood":5710,"clay":8310,"iron":3635,"crop":3115},"freeCrop":2},"buildingTime":39770},{"cost":{"resources":{"wood":7310,"clay":10635,"iron":4650,"crop":3990},"freeCrop":2},"buildingTime":46440},{"cost":{"resources":{"wood":9360,"clay":13610,"iron":5955,"crop":5105},"freeCrop":2},"buildingTime":54170},{"cost":{"resources":{"wood":11980,"clay":17420,"iron":7620,"crop":6535},"freeCrop":2},"buildingTime":63130}]