[{"cost":{"resources":{"wood":440,"clay":480,"iron":320,"crop":50},"freeCrop":3},"buildingTime":2840},{"cost":{"resources":{"wood":790,"clay":865,"iron":575,"crop":90},"freeCrop":2},"buildingTime":5460},{"cost":{"resources":{"wood":1425,"clay":1555,"iron":1035,"crop":160},"freeCrop":2},"buildingTime":9390},{"cost":{"resources":{"wood":2565,"clay":2800,"iron":1865,"crop":290},"freeCrop":2},"buildingTime":15290},{"cost":{"resources":{"wood":4620,"clay":5040,"iron":3360,"crop":525},"freeCrop":2},"buildingTime":24130}]